lazyscribe/__init__.py
lazyscribe/_meta.py
lazyscribe/_utils.py
lazyscribe/artifacts/__init__.py
lazyscribe/artifacts/base.py
lazyscribe/artifacts/json.py
lazyscribe/artifacts/pickle.py
lazyscribe/exception.py
lazyscribe/experiment.py
lazyscribe/linked.py
lazyscribe/project.py
lazyscribe/registry.py
lazyscribe/release.py
lazyscribe/repository.py
lazyscribe/test.py
lazyscribe-2.0.0.dist-info/WHEEL
lazyscribe-2.0.0.dist-info/entry_points.txt
lazyscribe-2.0.0.dist-info/METADATA
lazyscribe-2.0.0.dist-info/RECORD
