Metadata-Version: 2.3
Name: lazyscribe
Version: 2.0.0
Summary: Lightweight and lazy experiment logging
Author: Akshay Gupta
Author-email: Akshay Gupta <akgcodes@gmail.com>
License: MIT license
Classifier: Development Status :: 4 - Beta
Classifier: License :: OSI Approved :: MIT License
Classifier: Natural Language :: English
Classifier: Programming Language :: Python :: 3 :: Only
Classifier: Programming Language :: Python :: 3.10
Classifier: Programming Language :: Python :: 3.11
Classifier: Programming Language :: Python :: 3.12
Classifier: Programming Language :: Python :: 3.13
Classifier: Programming Language :: Python :: 3.14
Requires-Dist: attrs>=21.2.0,<=25.4.0
Requires-Dist: fsspec>=0.4.0,<=2025.12.0
Requires-Dist: python-slugify>=5.0.0,<=8.0.4
Requires-Dist: tomli>=2.2.1,<=2.3.0 ; python_full_version < '3.11'
Requires-Dist: commitizen ; extra == 'build'
Requires-Dist: uv ; extra == 'build'
Requires-Dist: lazyscribe[build] ; extra == 'dev'
Requires-Dist: lazyscribe[docs] ; extra == 'dev'
Requires-Dist: lazyscribe[qa] ; extra == 'dev'
Requires-Dist: lazyscribe[tests] ; extra == 'dev'
Requires-Dist: furo ; extra == 'docs'
Requires-Dist: matplotlib ; extra == 'docs'
Requires-Dist: pandas ; extra == 'docs'
Requires-Dist: pillow ; extra == 'docs'
Requires-Dist: scikit-learn ; extra == 'docs'
Requires-Dist: sphinx ; extra == 'docs'
Requires-Dist: sphinx-gallery ; extra == 'docs'
Requires-Dist: sphinx-inline-tabs ; extra == 'docs'
Requires-Dist: time-machine ; extra == 'docs'
Requires-Dist: edgetest ; extra == 'qa'
Requires-Dist: edgetest-pip-tools ; extra == 'qa'
Requires-Dist: mypy ; extra == 'qa'
Requires-Dist: pip-tools ; extra == 'qa'
Requires-Dist: pre-commit ; extra == 'qa'
Requires-Dist: pyproject-fmt ; extra == 'qa'
Requires-Dist: ruff ; extra == 'qa'
Requires-Dist: types-python-slugify ; extra == 'qa'
Requires-Dist: pytest ; extra == 'tests'
Requires-Dist: pytest-cov ; extra == 'tests'
Requires-Dist: requests ; extra == 'tests'
Requires-Dist: scikit-learn ; extra == 'tests'
Requires-Dist: time-machine ; extra == 'tests'
Requires-Python: >=3.10.0
Project-URL: documentation, https://lazyscribe.github.io/lazyscribe/
Project-URL: repository, https://github.com/lazyscribe/lazyscribe
Provides-Extra: build
Provides-Extra: dev
Provides-Extra: docs
Provides-Extra: qa
Provides-Extra: tests
